{
  "mse": 1.183608,
  "mae": 0.833934,
  "pearson_r": 0.983254,
  "mse_regime1": 1.037306,
  "mae_regime1": 0.810718,
  "pearson_r_regime1": 0.909509,
  "mse_regime2": 1.616718,
  "mae_regime2": 0.902662,
  "pearson_r_regime2": 0.977504,
  "mse_train": 1.027788,
  "mae_train": 0.807174,
  "pearson_r_train": 0.985353,
  "mse_train_regime1": 1.005421,
  "mse_train_regime2": 1.097016,
  "pearson_r_train_regime1": 0.910661,
  "pearson_r_train_regime2": 0.984849,
  "augmenter_name": "mlp_30",
  "n_features_total": 34,
  "n_features_augmented": 30,
  "augmenter_wall_clock": 0.0006,
  "circuit_depth": null,
  "qubit_count": null,
  "gate_count": null,
  "model_name": "ols",
  "chosen_alpha": null,
  "seed": 42,
  "total_wall_clock": 0.0036
}