{
  "mse": 2.916627,
  "mae": 1.29035,
  "pearson_r": 0.957551,
  "mse_regime1": 2.272526,
  "mae_regime1": 1.200633,
  "pearson_r_regime1": 0.794662,
  "mse_regime2": 4.829498,
  "mae_regime2": 1.556795,
  "pearson_r_regime2": 0.934154,
  "mse_train": 2.914256,
  "mae_train": 1.296863,
  "pearson_r_train": 0.957715,
  "mse_train_regime1": 2.326316,
  "mse_train_regime2": 4.654791,
  "pearson_r_train_regime1": 0.789157,
  "pearson_r_train_regime2": 0.935697,
  "augmenter_name": "unified_RZ_circular_cnot_XYZ",
  "n_features_total": 16,
  "n_features_augmented": 12,
  "augmenter_wall_clock": 6.2224,
  "n_trainable_params": 0,
  "n_random_params": 0,
  "effective_rank": 2.9179,
  "nonlinearity_score": 0.926048,
  "feature_target_alignment": 0.136601,
  "coef_l2_norm": 6.958275,
  "lasso_active_fraction": null,
  "circuit_depth": 7,
  "qubit_count": 4,
  "gate_count": 16,
  "model_name": "ridge",
  "chosen_alpha": 10.0,
  "seed": 789,
  "total_wall_clock": 0.023
}