{
  "mse": 2.932928,
  "mae": 1.294079,
  "pearson_r": 0.957309,
  "mse_regime1": 2.408654,
  "mae_regime1": 1.224602,
  "pearson_r_regime1": 0.787407,
  "mse_regime2": 4.489931,
  "mae_regime2": 1.500414,
  "pearson_r_regime2": 0.938066,
  "mse_train": 2.812624,
  "mae_train": 1.283846,
  "pearson_r_train": 0.95922,
  "mse_train_regime1": 2.413171,
  "mse_train_regime2": 3.995163,
  "pearson_r_train_regime1": 0.786276,
  "pearson_r_train_regime2": 0.944809,
  "augmenter_name": "unified_IQP_circular_cnot_full_rot_3L",
  "n_features_total": 34,
  "n_features_augmented": 30,
  "augmenter_wall_clock": 19.8201,
  "n_trainable_params": 0,
  "n_random_params": 48,
  "effective_rank": 20.6843,
  "nonlinearity_score": 0.763637,
  "feature_target_alignment": 0.225113,
  "coef_l2_norm": 18.486539,
  "lasso_active_fraction": null,
  "circuit_depth": 23,
  "qubit_count": 4,
  "gate_count": 44,
  "model_name": "ridge",
  "chosen_alpha": 0.1,
  "seed": 789,
  "total_wall_clock": 0.0294
}