{
  "mse": 3.563599,
  "mae": 1.374978,
  "pearson_r": 0.947869,
  "mse_regime1": 2.368757,
  "mae_regime1": 1.223735,
  "pearson_r_regime1": 0.79757,
  "mse_regime2": 7.112076,
  "mae_regime2": 1.824141,
  "pearson_r_regime2": 0.915095,
  "mse_train": 3.520968,
  "mae_train": 1.378765,
  "pearson_r_train": 0.948674,
  "mse_train_regime1": 2.419158,
  "mse_train_regime2": 6.782763,
  "pearson_r_train_regime1": 0.792366,
  "pearson_r_train_regime2": 0.917201,
  "augmenter_name": "unified_IQP_circular_cnot_Z+ZZ_3L_3ens",
  "n_features_total": 34,
  "n_features_augmented": 30,
  "augmenter_wall_clock": 31.9222,
  "n_trainable_params": 0,
  "n_random_params": 0,
  "effective_rank": 4.5959,
  "nonlinearity_score": 0.872157,
  "feature_target_alignment": 0.352295,
  "coef_l2_norm": 26.851471,
  "lasso_active_fraction": null,
  "circuit_depth": 19,
  "qubit_count": 4,
  "gate_count": 28,
  "model_name": "ridge",
  "chosen_alpha": 0.01,
  "seed": 789,
  "total_wall_clock": 0.0285
}