{
  "mse": 2.236571,
  "mae": 1.170076,
  "pearson_r": 0.967625,
  "mse_regime1": 2.163641,
  "mae_regime1": 1.170845,
  "pearson_r_regime1": 0.804116,
  "mse_regime2": 2.453162,
  "mae_regime2": 1.167791,
  "pearson_r_regime2": 0.965263,
  "mse_train": 2.228079,
  "mae_train": 1.173024,
  "pearson_r_train": 0.967837,
  "mse_train_regime1": 2.193783,
  "mse_train_regime2": 2.329609,
  "pearson_r_train_regime1": 0.801127,
  "pearson_r_train_regime2": 0.966683,
  "augmenter_name": "unified_RZ_all_cnot_rot_3L_3ens",
  "n_features_total": 16,
  "n_features_augmented": 12,
  "augmenter_wall_clock": 35.1928,
  "n_trainable_params": 0,
  "n_random_params": 144,
  "effective_rank": 7.8416,
  "nonlinearity_score": 0.530111,
  "feature_target_alignment": 0.485976,
  "coef_l2_norm": 29.110231,
  "lasso_active_fraction": null,
  "circuit_depth": 20,
  "qubit_count": 4,
  "gate_count": 46,
  "model_name": "ridge",
  "chosen_alpha": 0.1,
  "seed": 789,
  "total_wall_clock": 0.0191
}