{
  "mse": 2.087834,
  "mae": 1.076323,
  "pearson_r": 0.969796,
  "mse_regime1": 1.781762,
  "mae_regime1": 1.057274,
  "pearson_r_regime1": 0.84088,
  "mse_regime2": 2.996816,
  "mae_regime2": 1.132895,
  "pearson_r_regime2": 0.956959,
  "mse_train": 1.907243,
  "mae_train": 1.071555,
  "pearson_r_train": 0.972534,
  "mse_train_regime1": 1.853471,
  "mse_train_regime2": 2.066427,
  "pearson_r_train_regime1": 0.834006,
  "pearson_r_train_regime2": 0.970591,
  "augmenter_name": "unified_angle_circular_cnot_full",
  "n_features_total": 34,
  "n_features_augmented": 30,
  "augmenter_wall_clock": 13.4298,
  "n_trainable_params": 0,
  "n_random_params": 0,
  "effective_rank": 9.1278,
  "nonlinearity_score": 0.719471,
  "feature_target_alignment": 0.200267,
  "coef_l2_norm": 144.854359,
  "lasso_active_fraction": null,
  "circuit_depth": 5,
  "qubit_count": 4,
  "gate_count": 8,
  "model_name": "ridge",
  "chosen_alpha": 0.01,
  "seed": 789,
  "total_wall_clock": 0.0285
}