{
  "mse": 2.43209,
  "mae": 1.220923,
  "pearson_r": 0.96472,
  "mse_regime1": 2.114318,
  "mae_regime1": 1.155882,
  "pearson_r_regime1": 0.807748,
  "mse_regime2": 3.37582,
  "mae_regime2": 1.414082,
  "pearson_r_regime2": 0.95221,
  "mse_train": 2.466721,
  "mae_train": 1.224168,
  "pearson_r_train": 0.964329,
  "mse_train_regime1": 2.159258,
  "mse_train_regime2": 3.376932,
  "pearson_r_train_regime1": 0.803174,
  "pearson_r_train_regime2": 0.951914,
  "augmenter_name": "unified_IQP_linear_noc_Z+ZZ_rot_2ens",
  "n_features_total": 24,
  "n_features_augmented": 20,
  "augmenter_wall_clock": 17.8787,
  "n_trainable_params": 0,
  "n_random_params": 48,
  "effective_rank": 9.0195,
  "nonlinearity_score": 0.61516,
  "feature_target_alignment": 0.359553,
  "coef_l2_norm": 15.314934,
  "lasso_active_fraction": null,
  "circuit_depth": 8,
  "qubit_count": 4,
  "gate_count": 23,
  "model_name": "ridge",
  "chosen_alpha": 1.0,
  "seed": 789,
  "total_wall_clock": 0.0316
}