{
  "mse": 2.377807,
  "mae": 1.147306,
  "pearson_r": 0.966072,
  "mse_regime1": 1.757816,
  "mae_regime1": 1.04139,
  "pearson_r_regime1": 0.840876,
  "mse_regime2": 4.213227,
  "mae_regime2": 1.460857,
  "pearson_r_regime2": 0.941439,
  "mse_train": 2.324125,
  "mae_train": 1.14137,
  "pearson_r_train": 0.966562,
  "mse_train_regime1": 1.717076,
  "mse_train_regime2": 4.202941,
  "pearson_r_train_regime1": 0.841944,
  "pearson_r_train_regime2": 0.941862,
  "augmenter_name": "rff_15",
  "n_features_total": 19,
  "n_features_augmented": 15,
  "augmenter_wall_clock": 0.001,
  "n_trainable_params": 0,
  "n_random_params": 60,
  "effective_rank": 12.0168,
  "nonlinearity_score": 0.624211,
  "feature_target_alignment": 0.235271,
  "coef_l2_norm": 10.847467,
  "lasso_active_fraction": null,
  "circuit_depth": null,
  "qubit_count": null,
  "gate_count": null,
  "model_name": "ridge",
  "chosen_alpha": 1.0,
  "seed": 42,
  "total_wall_clock": 0.0327
}