{
  "mse": 2.180067,
  "mae": 1.158019,
  "pearson_r": 0.968475,
  "mse_regime1": 2.081884,
  "mae_regime1": 1.150936,
  "pearson_r_regime1": 0.811098,
  "mse_regime2": 2.471654,
  "mae_regime2": 1.179053,
  "pearson_r_regime2": 0.965186,
  "mse_train": 2.212948,
  "mae_train": 1.165306,
  "pearson_r_train": 0.968062,
  "mse_train_regime1": 2.141779,
  "mse_train_regime2": 2.423637,
  "pearson_r_train_regime1": 0.805376,
  "pearson_r_train_regime2": 0.965528,
  "augmenter_name": "reservoir_1x3_XYZ+ZZ",
  "n_features_total": 22,
  "n_features_augmented": 18,
  "augmenter_wall_clock": 12.0232,
  "n_trainable_params": 0,
  "n_random_params": 36,
  "effective_rank": 10.2995,
  "nonlinearity_score": 0.54952,
  "feature_target_alignment": 0.398693,
  "coef_l2_norm": 26.282664,
  "lasso_active_fraction": 1.0,
  "circuit_depth": 11,
  "qubit_count": 4,
  "gate_count": 22,
  "model_name": "lasso",
  "chosen_alpha": 0.001,
  "seed": 789,
  "total_wall_clock": 0.0273
}