{
  "mse": 2.382128,
  "mae": 1.218628,
  "pearson_r": 0.966229,
  "mse_regime1": 2.35522,
  "mae_regime1": 1.216864,
  "pearson_r_regime1": 0.77877,
  "mse_regime2": 2.46187,
  "mae_regime2": 1.223857,
  "pearson_r_regime2": 0.972459,
  "mse_train": 2.390568,
  "mae_train": 1.224782,
  "pearson_r_train": 0.964819,
  "mse_train_regime1": 2.340392,
  "mse_train_regime2": 2.541176,
  "pearson_r_train_regime1": 0.779307,
  "pearson_r_train_regime2": 0.972979,
  "augmenter_name": "oracle",
  "n_features_total": 6,
  "n_features_augmented": 2,
  "augmenter_wall_clock": 0.0001,
  "circuit_depth": null,
  "qubit_count": null,
  "gate_count": null,
  "model_name": "ols",
  "chosen_alpha": null,
  "seed": 1024,
  "total_wall_clock": 0.0008
}