{
  "mse": 3.474155,
  "mae": 1.435079,
  "pearson_r": 0.948741,
  "mse_regime1": 2.62352,
  "mae_regime1": 1.284809,
  "pearson_r_regime1": 0.760366,
  "mse_regime2": 6.057651,
  "mae_regime2": 1.89147,
  "pearson_r_regime2": 0.916549,
  "mse_train": 3.436489,
  "mae_train": 1.406908,
  "pearson_r_train": 0.949913,
  "mse_train_regime1": 2.525835,
  "mse_train_regime2": 6.274926,
  "pearson_r_train_regime1": 0.770251,
  "pearson_r_train_regime2": 0.918863,
  "augmenter_name": "unified_angle_all_cnot_XYZ_3L_2ens",
  "n_features_total": 28,
  "n_features_augmented": 24,
  "augmenter_wall_clock": 17.1932,
  "n_trainable_params": 0,
  "n_random_params": 0,
  "effective_rank": 4.5667,
  "nonlinearity_score": 0.54043,
  "feature_target_alignment": 0.192082,
  "coef_l2_norm": 5.243417,
  "lasso_active_fraction": null,
  "circuit_depth": 14,
  "qubit_count": 4,
  "gate_count": 22,
  "model_name": "ridge",
  "chosen_alpha": 10.0,
  "seed": 456,
  "total_wall_clock": 0.0254
}