{
  "mse": 2.292153,
  "mae": 1.172112,
  "pearson_r": 0.966507,
  "mse_regime1": 2.26963,
  "mae_regime1": 1.19257,
  "pearson_r_regime1": 0.787925,
  "mse_regime2": 2.360557,
  "mae_regime2": 1.109977,
  "pearson_r_regime2": 0.965844,
  "mse_train": 2.166851,
  "mae_train": 1.149372,
  "pearson_r_train": 0.96872,
  "mse_train_regime1": 2.17185,
  "mse_train_regime2": 2.151269,
  "pearson_r_train_regime1": 0.796582,
  "pearson_r_train_regime2": 0.970325,
  "augmenter_name": "unified_RZ_circular_cnot_full_2ens",
  "n_features_total": 64,
  "n_features_augmented": 60,
  "augmenter_wall_clock": 27.9362,
  "n_trainable_params": 0,
  "n_random_params": 0,
  "effective_rank": 5.4753,
  "nonlinearity_score": 0.928176,
  "feature_target_alignment": 0.15312,
  "coef_l2_norm": 16.990424,
  "lasso_active_fraction": null,
  "circuit_depth": 7,
  "qubit_count": 4,
  "gate_count": 16,
  "model_name": "ridge",
  "chosen_alpha": 0.1,
  "seed": 456,
  "total_wall_clock": 0.048
}