{
  "mse": 3.571486,
  "mae": 1.410749,
  "pearson_r": 0.94723,
  "mse_regime1": 2.125348,
  "mae_regime1": 1.155568,
  "pearson_r_regime1": 0.810992,
  "mse_regime2": 7.96361,
  "mae_regime2": 2.18577,
  "pearson_r_regime2": 0.89974,
  "mse_train": 3.623675,
  "mae_train": 1.38714,
  "pearson_r_train": 0.947109,
  "mse_train_regime1": 2.07146,
  "mse_train_regime2": 8.461803,
  "pearson_r_train_regime1": 0.81531,
  "pearson_r_train_regime2": 0.897997,
  "augmenter_name": "unified_IQP_all_noc_XYZ_rot_3L",
  "n_features_total": 16,
  "n_features_augmented": 12,
  "augmenter_wall_clock": 8.9821,
  "n_trainable_params": 0,
  "n_random_params": 48,
  "effective_rank": 5.8039,
  "nonlinearity_score": 0.809121,
  "feature_target_alignment": 0.250829,
  "coef_l2_norm": 10.533049,
  "lasso_active_fraction": null,
  "circuit_depth": 12,
  "qubit_count": 4,
  "gate_count": 34,
  "model_name": "ridge",
  "chosen_alpha": 0.1,
  "seed": 456,
  "total_wall_clock": 0.0191
}