{
  "mse": 2.177067,
  "mae": 1.119064,
  "pearson_r": 0.968159,
  "mse_regime1": 1.736736,
  "mae_regime1": 1.042646,
  "pearson_r_regime1": 0.841402,
  "mse_regime2": 3.514416,
  "mae_regime2": 1.351156,
  "pearson_r_regime2": 0.948654,
  "mse_train": 2.108534,
  "mae_train": 1.100051,
  "pearson_r_train": 0.969575,
  "mse_train_regime1": 1.685556,
  "mse_train_regime2": 3.426922,
  "pearson_r_train_regime1": 0.845147,
  "pearson_r_train_regime2": 0.951929,
  "augmenter_name": "unified_IQP_linear_noc_full_rot_2L",
  "n_features_total": 34,
  "n_features_augmented": 30,
  "augmenter_wall_clock": 15.7303,
  "n_trainable_params": 0,
  "n_random_params": 36,
  "effective_rank": 12.4781,
  "nonlinearity_score": 0.691203,
  "feature_target_alignment": 0.304593,
  "coef_l2_norm": 17.04837,
  "lasso_active_fraction": null,
  "circuit_depth": 9,
  "qubit_count": 4,
  "gate_count": 27,
  "model_name": "ridge",
  "chosen_alpha": 1.0,
  "seed": 456,
  "total_wall_clock": 0.0289
}