{
  "mse": 2.542821,
  "mae": 1.224955,
  "pearson_r": 0.96274,
  "mse_regime1": 2.008682,
  "mae_regime1": 1.12957,
  "pearson_r_regime1": 0.813926,
  "mse_regime2": 4.165075,
  "mae_regime2": 1.514654,
  "pearson_r_regime2": 0.93902,
  "mse_train": 2.486025,
  "mae_train": 1.201589,
  "pearson_r_train": 0.964026,
  "mse_train_regime1": 1.918007,
  "mse_train_regime2": 4.25649,
  "pearson_r_train_regime1": 0.821793,
  "pearson_r_train_regime2": 0.939976,
  "augmenter_name": "unified_RZ_all_cnot_Z+ZZ_rot",
  "n_features_total": 14,
  "n_features_augmented": 10,
  "augmenter_wall_clock": 10.2707,
  "n_trainable_params": 0,
  "n_random_params": 24,
  "effective_rank": 6.3028,
  "nonlinearity_score": 0.524335,
  "feature_target_alignment": 0.432488,
  "coef_l2_norm": 20.685919,
  "lasso_active_fraction": null,
  "circuit_depth": 10,
  "qubit_count": 4,
  "gate_count": 26,
  "model_name": "ridge",
  "chosen_alpha": 0.1,
  "seed": 456,
  "total_wall_clock": 0.0198
}