{
  "mse": 3.232225,
  "mae": 1.342766,
  "pearson_r": 0.952353,
  "mse_regime1": 2.217618,
  "mae_regime1": 1.176198,
  "pearson_r_regime1": 0.800776,
  "mse_regime2": 6.313731,
  "mae_regime2": 1.848655,
  "pearson_r_regime2": 0.914646,
  "mse_train": 3.230086,
  "mae_train": 1.321543,
  "pearson_r_train": 0.952996,
  "mse_train_regime1": 2.159985,
  "mse_train_regime2": 6.565503,
  "pearson_r_train_regime1": 0.806302,
  "pearson_r_train_regime2": 0.916089,
  "augmenter_name": "unified_IQP_circular_noc_XYZ_2L_2ens",
  "n_features_total": 28,
  "n_features_augmented": 24,
  "augmenter_wall_clock": 11.4576,
  "n_trainable_params": 0,
  "n_random_params": 0,
  "effective_rank": 5.952,
  "nonlinearity_score": 0.820921,
  "feature_target_alignment": 0.206913,
  "coef_l2_norm": 7.291349,
  "lasso_active_fraction": null,
  "circuit_depth": 7,
  "qubit_count": 4,
  "gate_count": 16,
  "model_name": "ridge",
  "chosen_alpha": 1.0,
  "seed": 456,
  "total_wall_clock": 0.0252
}