{
  "mse": 2.886935,
  "mae": 1.322692,
  "pearson_r": 0.957563,
  "mse_regime1": 2.44427,
  "mae_regime1": 1.244376,
  "pearson_r_regime1": 0.773241,
  "mse_regime2": 4.231372,
  "mae_regime2": 1.560551,
  "pearson_r_regime2": 0.939105,
  "mse_train": 2.832105,
  "mae_train": 1.293247,
  "pearson_r_train": 0.958912,
  "mse_train_regime1": 2.321684,
  "mse_train_regime2": 4.423048,
  "pearson_r_train_regime1": 0.784912,
  "pearson_r_train_regime2": 0.940108,
  "augmenter_name": "unified_IQP_linear_cnot_Z+ZZ_rot_2L",
  "n_features_total": 14,
  "n_features_augmented": 10,
  "augmenter_wall_clock": 11.7694,
  "n_trainable_params": 0,
  "n_random_params": 36,
  "effective_rank": 7.6059,
  "nonlinearity_score": 0.653953,
  "feature_target_alignment": 0.202861,
  "coef_l2_norm": 10.411175,
  "lasso_active_fraction": null,
  "circuit_depth": 13,
  "qubit_count": 4,
  "gate_count": 33,
  "model_name": "ridge",
  "chosen_alpha": 1.0,
  "seed": 456,
  "total_wall_clock": 0.0203
}