{
  "mse": 2.359067,
  "mae": 1.133209,
  "pearson_r": 0.965466,
  "mse_regime1": 1.752453,
  "mae_regime1": 1.044287,
  "pearson_r_regime1": 0.841681,
  "mse_regime2": 4.201439,
  "mae_regime2": 1.403275,
  "pearson_r_regime2": 0.938658,
  "mse_train": 2.296565,
  "mae_train": 1.107913,
  "pearson_r_train": 0.966818,
  "mse_train_regime1": 1.708099,
  "mse_train_regime2": 4.130767,
  "pearson_r_train_regime1": 0.845264,
  "pearson_r_train_regime2": 0.942848,
  "augmenter_name": "unified_IQP_all_cnot_full_rot_3ens",
  "n_features_total": 94,
  "n_features_augmented": 90,
  "augmenter_wall_clock": 51.5904,
  "n_trainable_params": 0,
  "n_random_params": 72,
  "effective_rank": 32.5376,
  "nonlinearity_score": 0.793438,
  "feature_target_alignment": 0.197935,
  "coef_l2_norm": 27.910705,
  "lasso_active_fraction": null,
  "circuit_depth": 14,
  "qubit_count": 4,
  "gate_count": 32,
  "model_name": "ridge",
  "chosen_alpha": 1.0,
  "seed": 456,
  "total_wall_clock": 0.0812
}