{
  "mse": 3.460048,
  "mae": 1.39471,
  "pearson_r": 0.950554,
  "mse_regime1": 2.394437,
  "mae_regime1": 1.233014,
  "pearson_r_regime1": 0.782107,
  "mse_regime2": 6.618025,
  "mae_regime2": 1.873901,
  "pearson_r_regime2": 0.914513,
  "mse_train": 3.444341,
  "mae_train": 1.403339,
  "pearson_r_train": 0.948897,
  "mse_train_regime1": 2.406746,
  "mse_train_regime2": 6.558789,
  "pearson_r_train_regime1": 0.779719,
  "pearson_r_train_regime2": 0.919762,
  "augmenter_name": "unified_IQP_linear_cnot_2L_2ens",
  "n_features_total": 12,
  "n_features_augmented": 8,
  "augmenter_wall_clock": 12.1072,
  "n_trainable_params": 0,
  "n_random_params": 0,
  "effective_rank": 2.9654,
  "nonlinearity_score": 0.857997,
  "feature_target_alignment": 0.370051,
  "coef_l2_norm": 5.514254,
  "lasso_active_fraction": null,
  "circuit_depth": 10,
  "qubit_count": 4,
  "gate_count": 21,
  "model_name": "ridge",
  "chosen_alpha": 1.0,
  "seed": 1024,
  "total_wall_clock": 0.0185
}