{
  "mse": 1.918003,
  "mae": 1.037318,
  "pearson_r": 0.9729,
  "mse_regime1": 1.341108,
  "mae_regime1": 0.912033,
  "pearson_r_regime1": 0.88012,
  "mse_regime2": 3.62765,
  "mae_regime2": 1.408606,
  "pearson_r_regime2": 0.947106,
  "mse_train": 1.858697,
  "mae_train": 1.028565,
  "pearson_r_train": 0.972757,
  "mse_train_regime1": 1.349697,
  "mse_train_regime2": 3.386512,
  "pearson_r_train_regime1": 0.878943,
  "pearson_r_train_regime2": 0.952686,
  "augmenter_name": "unified_IQP_linear_noc_full_rot_3L_2ens",
  "n_features_total": 64,
  "n_features_augmented": 60,
  "augmenter_wall_clock": 32.4121,
  "n_trainable_params": 0,
  "n_random_params": 96,
  "effective_rank": 17.0063,
  "nonlinearity_score": 0.666267,
  "feature_target_alignment": 0.31559,
  "coef_l2_norm": 16.786625,
  "lasso_active_fraction": null,
  "circuit_depth": 10,
  "qubit_count": 4,
  "gate_count": 31,
  "model_name": "ridge",
  "chosen_alpha": 1.0,
  "seed": 1024,
  "total_wall_clock": 0.0434
}