{
  "mse": 1.384494,
  "mae": 0.910876,
  "pearson_r": 0.980516,
  "mse_regime1": 1.175215,
  "mae_regime1": 0.864734,
  "pearson_r_regime1": 0.895902,
  "mse_regime2": 2.004701,
  "mae_regime2": 1.047619,
  "pearson_r_regime2": 0.971126,
  "mse_train": 1.369746,
  "mae_train": 0.9032,
  "pearson_r_train": 0.979997,
  "mse_train_regime1": 1.184456,
  "mse_train_regime2": 1.925913,
  "pearson_r_train_regime1": 0.894581,
  "pearson_r_train_regime2": 0.973201,
  "augmenter_name": "unified_angle_circular_cnot_XYZ_rot_3L_3ens",
  "n_features_total": 40,
  "n_features_augmented": 36,
  "augmenter_wall_clock": 31.7658,
  "n_trainable_params": 0,
  "n_random_params": 144,
  "effective_rank": 18.9378,
  "nonlinearity_score": 0.641709,
  "feature_target_alignment": 0.330822,
  "coef_l2_norm": 48.454691,
  "lasso_active_fraction": null,
  "circuit_depth": 17,
  "qubit_count": 4,
  "gate_count": 32,
  "model_name": "ridge",
  "chosen_alpha": 0.01,
  "seed": 1024,
  "total_wall_clock": 0.0349
}