{
  "mse": 1.346029,
  "mae": 0.907636,
  "pearson_r": 0.98106,
  "mse_regime1": 1.159523,
  "mae_regime1": 0.857975,
  "pearson_r_regime1": 0.897315,
  "mse_regime2": 1.898744,
  "mae_regime2": 1.054807,
  "pearson_r_regime2": 0.972734,
  "mse_train": 1.356528,
  "mae_train": 0.903549,
  "pearson_r_train": 0.980192,
  "mse_train_regime1": 1.1619,
  "mse_train_regime2": 1.940725,
  "pearson_r_train_regime1": 0.896773,
  "pearson_r_train_regime2": 0.973002,
  "augmenter_name": "unified_RZ_linear_noc_full_rot_3L",
  "n_features_total": 34,
  "n_features_augmented": 30,
  "augmenter_wall_clock": 15.4358,
  "n_trainable_params": 0,
  "n_random_params": 48,
  "effective_rank": 12.2501,
  "nonlinearity_score": 0.572186,
  "feature_target_alignment": 0.36088,
  "coef_l2_norm": 38.059067,
  "lasso_active_fraction": null,
  "circuit_depth": 7,
  "qubit_count": 4,
  "gate_count": 28,
  "model_name": "ridge",
  "chosen_alpha": 0.01,
  "seed": 1024,
  "total_wall_clock": 0.0317
}