{
  "mse": 1.332241,
  "mae": 0.905908,
  "pearson_r": 0.981257,
  "mse_regime1": 1.165612,
  "mae_regime1": 0.860456,
  "pearson_r_regime1": 0.896761,
  "mse_regime2": 1.826052,
  "mae_regime2": 1.040606,
  "pearson_r_regime2": 0.97378,
  "mse_train": 1.352209,
  "mae_train": 0.90336,
  "pearson_r_train": 0.980255,
  "mse_train_regime1": 1.168671,
  "mse_train_regime2": 1.903114,
  "pearson_r_train_regime1": 0.896088,
  "pearson_r_train_regime2": 0.973522,
  "augmenter_name": "unified_angle_linear_noc_full_rot",
  "n_features_total": 34,
  "n_features_augmented": 30,
  "augmenter_wall_clock": 13.8565,
  "n_trainable_params": 0,
  "n_random_params": 24,
  "effective_rank": 12.3384,
  "nonlinearity_score": 0.589328,
  "feature_target_alignment": 0.378489,
  "coef_l2_norm": 21.953232,
  "lasso_active_fraction": null,
  "circuit_depth": 3,
  "qubit_count": 4,
  "gate_count": 12,
  "model_name": "ridge",
  "chosen_alpha": 0.1,
  "seed": 1024,
  "total_wall_clock": 0.0311
}