{
  "mse": 3.814261,
  "mae": 1.430795,
  "pearson_r": 0.945371,
  "mse_regime1": 2.276898,
  "mae_regime1": 1.192076,
  "pearson_r_regime1": 0.799827,
  "mse_regime2": 8.370293,
  "mae_regime2": 2.13825,
  "pearson_r_regime2": 0.90531,
  "mse_train": 3.782501,
  "mae_train": 1.440379,
  "pearson_r_train": 0.943731,
  "mse_train_regime1": 2.3256,
  "mse_train_regime2": 8.155536,
  "pearson_r_train_regime1": 0.795199,
  "pearson_r_train_regime2": 0.912174,
  "augmenter_name": "unified_IQP_all_cnot_XYZ_2L_3ens",
  "n_features_total": 40,
  "n_features_augmented": 36,
  "augmenter_wall_clock": 27.1153,
  "n_trainable_params": 0,
  "n_random_params": 0,
  "effective_rank": 5.7454,
  "nonlinearity_score": 0.902921,
  "feature_target_alignment": 0.11446,
  "coef_l2_norm": 5.415945,
  "lasso_active_fraction": null,
  "circuit_depth": 16,
  "qubit_count": 4,
  "gate_count": 30,
  "model_name": "ridge",
  "chosen_alpha": 10.0,
  "seed": 1024,
  "total_wall_clock": 0.0305
}