{
  "mse": 3.405576,
  "mae": 1.345238,
  "pearson_r": 0.951367,
  "mse_regime1": 2.34069,
  "mae_regime1": 1.210153,
  "pearson_r_regime1": 0.797301,
  "mse_regime2": 6.561402,
  "mae_regime2": 1.745566,
  "pearson_r_regime2": 0.916562,
  "mse_train": 3.341045,
  "mae_train": 1.342086,
  "pearson_r_train": 0.95047,
  "mse_train_regime1": 2.326288,
  "mse_train_regime2": 6.386939,
  "pearson_r_train_regime1": 0.795625,
  "pearson_r_train_regime2": 0.922158,
  "augmenter_name": "unified_IQP_circular_cnot_full_2L_3ens",
  "n_features_total": 94,
  "n_features_augmented": 90,
  "augmenter_wall_clock": 47.5406,
  "n_trainable_params": 0,
  "n_random_params": 0,
  "effective_rank": 10.038,
  "nonlinearity_score": 0.944798,
  "feature_target_alignment": 0.118705,
  "coef_l2_norm": 5.587563,
  "lasso_active_fraction": null,
  "circuit_depth": 15,
  "qubit_count": 4,
  "gate_count": 24,
  "model_name": "ridge",
  "chosen_alpha": 10.0,
  "seed": 1024,
  "total_wall_clock": 0.086
}