{
  "mse": 2.106595,
  "mae": 1.13397,
  "pearson_r": 0.970196,
  "mse_regime1": 2.148688,
  "mae_regime1": 1.163554,
  "pearson_r_regime1": 0.80089,
  "mse_regime2": 1.981848,
  "mae_regime2": 1.046298,
  "pearson_r_regime2": 0.971763,
  "mse_train": 2.083409,
  "mae_train": 1.133246,
  "pearson_r_train": 0.969411,
  "mse_train_regime1": 2.164147,
  "mse_train_regime2": 1.841065,
  "pearson_r_train_regime1": 0.79801,
  "pearson_r_train_regime2": 0.974918,
  "augmenter_name": "unified_angle_linear_cnot_Z+ZZ_2L_3ens",
  "n_features_total": 34,
  "n_features_augmented": 30,
  "augmenter_wall_clock": 23.2127,
  "n_trainable_params": 0,
  "n_random_params": 0,
  "effective_rank": 5.0119,
  "nonlinearity_score": 0.8355,
  "feature_target_alignment": 0.36543,
  "coef_l2_norm": 5.255482,
  "lasso_active_fraction": null,
  "circuit_depth": 6,
  "qubit_count": 4,
  "gate_count": 10,
  "model_name": "ridge",
  "chosen_alpha": 10.0,
  "seed": 1024,
  "total_wall_clock": 0.029
}