{
  "mse": 1.284571,
  "mae": 0.883449,
  "pearson_r": 0.981817,
  "mse_regime1": 1.119369,
  "mae_regime1": 0.839733,
  "pearson_r_regime1": 0.902042,
  "mse_regime2": 1.773634,
  "mae_regime2": 1.012865,
  "pearson_r_regime2": 0.97528,
  "mse_train": 1.2101,
  "mae_train": 0.865013,
  "pearson_r_train": 0.982732,
  "mse_train_regime1": 1.097881,
  "mse_train_regime2": 1.55742,
  "pearson_r_train_regime1": 0.902023,
  "pearson_r_train_regime2": 0.978422,
  "augmenter_name": "unified_RZ_circular_cnot_full_rot_3ens",
  "n_features_total": 94,
  "n_features_augmented": 90,
  "augmenter_wall_clock": 47.1283,
  "n_trainable_params": 0,
  "n_random_params": 72,
  "effective_rank": 23.437,
  "nonlinearity_score": 0.620063,
  "feature_target_alignment": 0.283918,
  "coef_l2_norm": 135.53104,
  "lasso_active_fraction": null,
  "circuit_depth": 9,
  "qubit_count": 4,
  "gate_count": 24,
  "model_name": "ridge",
  "chosen_alpha": 0.001,
  "seed": 42,
  "total_wall_clock": 0.0739
}