{
  "mse": 2.592713,
  "mae": 1.149599,
  "pearson_r": 0.962927,
  "mse_regime1": 1.540404,
  "mae_regime1": 0.966939,
  "pearson_r_regime1": 0.870436,
  "mse_regime2": 5.707966,
  "mae_regime2": 1.690347,
  "pearson_r_regime2": 0.930178,
  "mse_train": 2.50434,
  "mae_train": 1.127017,
  "pearson_r_train": 0.963922,
  "mse_train_regime1": 1.469323,
  "mse_train_regime2": 5.707723,
  "pearson_r_train_regime1": 0.872724,
  "pearson_r_train_regime2": 0.929489,
  "augmenter_name": "unified_IQP_all_noc_full_rot_2L_2ens",
  "n_features_total": 64,
  "n_features_augmented": 60,
  "augmenter_wall_clock": 32.8524,
  "n_trainable_params": 0,
  "n_random_params": 72,
  "effective_rank": 23.1391,
  "nonlinearity_score": 0.802456,
  "feature_target_alignment": 0.214331,
  "coef_l2_norm": 8.14819,
  "lasso_active_fraction": null,
  "circuit_depth": 11,
  "qubit_count": 4,
  "gate_count": 30,
  "model_name": "ridge",
  "chosen_alpha": 10.0,
  "seed": 42,
  "total_wall_clock": 0.0429
}