{
  "mse": 2.525207,
  "mae": 1.171242,
  "pearson_r": 0.963925,
  "mse_regime1": 1.643715,
  "mae_regime1": 1.00821,
  "pearson_r_regime1": 0.852288,
  "mse_regime2": 5.134773,
  "mae_regime2": 1.653879,
  "pearson_r_regime2": 0.929024,
  "mse_train": 2.453339,
  "mae_train": 1.158134,
  "pearson_r_train": 0.964669,
  "mse_train_regime1": 1.583173,
  "mse_train_regime2": 5.146508,
  "pearson_r_train_regime1": 0.855639,
  "pearson_r_train_regime2": 0.928943,
  "augmenter_name": "unified_IQP_linear_cnot_rot_3L_3ens",
  "n_features_total": 16,
  "n_features_augmented": 12,
  "augmenter_wall_clock": 30.5039,
  "n_trainable_params": 0,
  "n_random_params": 144,
  "effective_rank": 10.1184,
  "nonlinearity_score": 0.800507,
  "feature_target_alignment": 0.206054,
  "coef_l2_norm": 10.183547,
  "lasso_active_fraction": null,
  "circuit_depth": 16,
  "qubit_count": 4,
  "gate_count": 40,
  "model_name": "ridge",
  "chosen_alpha": 1.0,
  "seed": 42,
  "total_wall_clock": 0.0185
}