{
  "mse": 2.186454,
  "mae": 1.090926,
  "pearson_r": 0.968831,
  "mse_regime1": 1.463526,
  "mae_regime1": 0.941115,
  "pearson_r_regime1": 0.874548,
  "mse_regime2": 4.326608,
  "mae_regime2": 1.534426,
  "pearson_r_regime2": 0.943069,
  "mse_train": 2.173632,
  "mae_train": 1.075557,
  "pearson_r_train": 0.968762,
  "mse_train_regime1": 1.432587,
  "mse_train_regime2": 4.467168,
  "pearson_r_train_regime1": 0.873932,
  "pearson_r_train_regime2": 0.940842,
  "augmenter_name": "unified_IQP_circular_noc_full_rot_2L_2ens",
  "n_features_total": 64,
  "n_features_augmented": 60,
  "augmenter_wall_clock": 31.5699,
  "n_trainable_params": 0,
  "n_random_params": 72,
  "effective_rank": 19.973,
  "nonlinearity_score": 0.72938,
  "feature_target_alignment": 0.268736,
  "coef_l2_norm": 11.960709,
  "lasso_active_fraction": null,
  "circuit_depth": 10,
  "qubit_count": 4,
  "gate_count": 28,
  "model_name": "ridge",
  "chosen_alpha": 1.0,
  "seed": 42,
  "total_wall_clock": 0.0431
}