{
  "mse": 3.270596,
  "mae": 1.32961,
  "pearson_r": 0.953035,
  "mse_regime1": 2.152129,
  "mae_regime1": 1.14687,
  "pearson_r_regime1": 0.811362,
  "mse_regime2": 6.581702,
  "mae_regime2": 1.870591,
  "pearson_r_regime2": 0.915024,
  "mse_train": 3.209006,
  "mae_train": 1.316918,
  "pearson_r_train": 0.953522,
  "mse_train_regime1": 2.073543,
  "mse_train_regime2": 6.723267,
  "pearson_r_train_regime1": 0.815121,
  "pearson_r_train_regime2": 0.912418,
  "augmenter_name": "unified_IQP_circular_cnot_Z+ZZ_rot_3L",
  "n_features_total": 14,
  "n_features_augmented": 10,
  "augmenter_wall_clock": 14.0016,
  "n_trainable_params": 0,
  "n_random_params": 48,
  "effective_rank": 8.9339,
  "nonlinearity_score": 0.799111,
  "feature_target_alignment": 0.169359,
  "coef_l2_norm": 10.939117,
  "lasso_active_fraction": null,
  "circuit_depth": 23,
  "qubit_count": 4,
  "gate_count": 44,
  "model_name": "ridge",
  "chosen_alpha": 1.0,
  "seed": 42,
  "total_wall_clock": 0.0187
}