{
  "mse": 1.348355,
  "mae": 0.899204,
  "pearson_r": 0.980917,
  "mse_regime1": 1.160796,
  "mae_regime1": 0.851411,
  "pearson_r_regime1": 0.898222,
  "mse_regime2": 1.903604,
  "mae_regime2": 1.040691,
  "pearson_r_regime2": 0.973497,
  "mse_train": 1.269947,
  "mae_train": 0.882719,
  "pearson_r_train": 0.98187,
  "mse_train_regime1": 1.131369,
  "mse_train_regime2": 1.698847,
  "pearson_r_train_regime1": 0.898848,
  "pearson_r_train_regime2": 0.976438,
  "augmenter_name": "unified_angle_circular_cnot_prob_rot_3L_3ens",
  "n_features_total": 52,
  "n_features_augmented": 48,
  "augmenter_wall_clock": 28.7557,
  "n_trainable_params": 0,
  "n_random_params": 144,
  "effective_rank": 18.1533,
  "nonlinearity_score": 0.643978,
  "feature_target_alignment": 0.274736,
  "coef_l2_norm": 130.804343,
  "lasso_active_fraction": null,
  "circuit_depth": 17,
  "qubit_count": 4,
  "gate_count": 32,
  "model_name": "ridge",
  "chosen_alpha": 0.001,
  "seed": 42,
  "total_wall_clock": 0.0361
}