{
  "mse": 2.933075,
  "mae": 1.29001,
  "pearson_r": 0.957967,
  "mse_regime1": 2.419284,
  "mae_regime1": 1.220072,
  "pearson_r_regime1": 0.790346,
  "mse_regime2": 4.4541,
  "mae_regime2": 1.497055,
  "pearson_r_regime2": 0.944336,
  "mse_train": 2.848139,
  "mae_train": 1.283738,
  "pearson_r_train": 0.958861,
  "mse_train_regime1": 2.371198,
  "mse_train_regime2": 4.324276,
  "pearson_r_train_regime1": 0.790967,
  "pearson_r_train_regime2": 0.945605,
  "augmenter_name": "unified_RZ_all_cnot_rot_2L",
  "n_features_total": 8,
  "n_features_augmented": 4,
  "augmenter_wall_clock": 9.5017,
  "n_trainable_params": 0,
  "n_random_params": 36,
  "effective_rank": 3.3929,
  "nonlinearity_score": 0.726365,
  "feature_target_alignment": 0.286226,
  "coef_l2_norm": 8.755549,
  "lasso_active_fraction": null,
  "circuit_depth": 15,
  "qubit_count": 4,
  "gate_count": 36,
  "model_name": "ridge",
  "chosen_alpha": 0.1,
  "seed": 42,
  "total_wall_clock": 0.0156
}