{
  "mse": 1.532588,
  "mae": 0.973864,
  "pearson_r": 0.977695,
  "mse_regime1": 1.437686,
  "mae_regime1": 0.950884,
  "pearson_r_regime1": 0.871125,
  "mse_regime2": 1.82082,
  "mae_regime2": 1.043658,
  "pearson_r_regime2": 0.973867,
  "mse_train": 1.489517,
  "mae_train": 0.954686,
  "pearson_r_train": 0.978614,
  "mse_train_regime1": 1.373217,
  "mse_train_regime2": 1.852013,
  "pearson_r_train_regime1": 0.876094,
  "pearson_r_train_regime2": 0.974323,
  "augmenter_name": "reservoir_5x3_XYZ+ZZ",
  "n_features_total": 94,
  "n_features_augmented": 90,
  "augmenter_wall_clock": 56.839,
  "n_trainable_params": 0,
  "n_random_params": 180,
  "effective_rank": 18.4422,
  "nonlinearity_score": 0.590435,
  "feature_target_alignment": 0.344042,
  "coef_l2_norm": 30.310306,
  "lasso_active_fraction": 0.425532,
  "circuit_depth": 11,
  "qubit_count": 4,
  "gate_count": 22,
  "model_name": "lasso",
  "chosen_alpha": 0.001,
  "seed": 456,
  "total_wall_clock": 0.3311
}