{
  "mse": 1.588384,
  "mae": 0.953939,
  "pearson_r": 0.976918,
  "mse_regime1": 1.300535,
  "mae_regime1": 0.908133,
  "pearson_r_regime1": 0.884843,
  "mse_regime2": 2.462621,
  "mae_regime2": 1.09306,
  "pearson_r_regime2": 0.965069,
  "mse_train": 1.372139,
  "mae_train": 0.916548,
  "pearson_r_train": 0.980311,
  "mse_train_regime1": 1.235334,
  "mse_train_regime2": 1.798551,
  "pearson_r_train_regime1": 0.889896,
  "pearson_r_train_regime2": 0.975131,
  "augmenter_name": "rff_96",
  "n_features_total": 100,
  "n_features_augmented": 96,
  "augmenter_wall_clock": 0.0058,
  "n_trainable_params": 0,
  "n_random_params": 384,
  "effective_rank": 36.8659,
  "nonlinearity_score": 0.609407,
  "feature_target_alignment": 0.280038,
  "coef_l2_norm": 87.860049,
  "lasso_active_fraction": null,
  "circuit_depth": null,
  "qubit_count": null,
  "gate_count": null,
  "model_name": "ridge",
  "chosen_alpha": 0.1,
  "seed": 456,
  "total_wall_clock": 0.0499
}