{
  "mse": 4.645581,
  "mae": 1.607409,
  "pearson_r": 0.933023,
  "mse_regime1": 3.008822,
  "mae_regime1": 1.379672,
  "pearson_r_regime1": 0.784627,
  "mse_regime2": 9.496173,
  "mae_regime2": 2.282315,
  "pearson_r_regime2": 0.921912,
  "mse_train": 4.611526,
  "mae_train": 1.616563,
  "pearson_r_train": 0.930944,
  "mse_train_regime1": 3.006976,
  "mse_train_regime2": 9.427746,
  "pearson_r_train_regime1": 0.781314,
  "pearson_r_train_regime2": 0.927116,
  "augmenter_name": "iqp_5q_r3",
  "n_features_total": 19,
  "n_features_augmented": 15,
  "augmenter_wall_clock": 12.795,
  "n_trainable_params": 0,
  "n_random_params": 0,
  "effective_rank": 7.9023,
  "nonlinearity_score": 0.948133,
  "feature_target_alignment": 0.130921,
  "coef_l2_norm": 5.263637,
  "lasso_active_fraction": null,
  "circuit_depth": 1,
  "qubit_count": 5,
  "gate_count": 1,
  "model_name": "ridge",
  "chosen_alpha": 10.0,
  "seed": 1024,
  "total_wall_clock": 0.0205
}