{
  "mse": 1.416233,
  "mae": 0.924965,
  "pearson_r": 0.979511,
  "mse_regime1": 1.219409,
  "mae_regime1": 0.875903,
  "pearson_r_regime1": 0.889757,
  "mse_regime2": 2.000767,
  "mae_regime2": 1.070673,
  "pearson_r_regime2": 0.970803,
  "mse_train": 1.396122,
  "mae_train": 0.917782,
  "pearson_r_train": 0.979019,
  "mse_train_regime1": 1.2123,
  "mse_train_regime2": 1.988906,
  "pearson_r_train_regime1": 0.891625,
  "pearson_r_train_regime2": 0.971251,
  "augmenter_name": "reservoir_1x3_full_6q",
  "n_features_total": 67,
  "n_features_augmented": 63,
  "augmenter_wall_clock": 28.2206,
  "n_trainable_params": 0,
  "n_random_params": 54,
  "effective_rank": 22.3,
  "nonlinearity_score": 0.60393,
  "feature_target_alignment": 0.317788,
  "coef_l2_norm": 32.434505,
  "lasso_active_fraction": 0.567164,
  "circuit_depth": 13,
  "qubit_count": 6,
  "gate_count": 34,
  "model_name": "lasso",
  "chosen_alpha": 0.001,
  "seed": 123,
  "total_wall_clock": 0.0888
}