{
  "mse": 1.110217,
  "mae": 0.8377,
  "pearson_r": 0.983974,
  "mse_regime1": 1.044243,
  "mae_regime1": 0.816984,
  "pearson_r_regime1": 0.906391,
  "mse_regime2": 1.30615,
  "mae_regime2": 0.89922,
  "pearson_r_regime2": 0.981108,
  "mse_train": 1.048687,
  "mae_train": 0.814112,
  "pearson_r_train": 0.984274,
  "mse_train_regime1": 1.025261,
  "mse_train_regime2": 1.124231,
  "pearson_r_train_regime1": 0.909015,
  "pearson_r_train_regime2": 0.983761,
  "augmenter_name": "mlp_30",
  "n_features_total": 34,
  "n_features_augmented": 30,
  "augmenter_wall_clock": 0.001,
  "circuit_depth": null,
  "qubit_count": null,
  "gate_count": null,
  "model_name": "ols",
  "chosen_alpha": null,
  "seed": 123,
  "total_wall_clock": 0.0034
}