{
  "mse": 4.179229,
  "mae": 1.525972,
  "pearson_r": 0.939525,
  "mse_regime1": 2.572926,
  "mae_regime1": 1.271376,
  "pearson_r_regime1": 0.793414,
  "mse_regime2": 8.93452,
  "mae_regime2": 2.279678,
  "pearson_r_regime2": 0.922844,
  "mse_train": 4.118956,
  "mae_train": 1.51592,
  "pearson_r_train": 0.939926,
  "mse_train_regime1": 2.534927,
  "mse_train_regime2": 9.021531,
  "pearson_r_train_regime1": 0.792963,
  "pearson_r_train_regime2": 0.917204,
  "augmenter_name": "iqp_10q_r3",
  "n_features_total": 59,
  "n_features_augmented": 55,
  "augmenter_wall_clock": 37.2612,
  "n_trainable_params": 0,
  "n_random_params": 0,
  "effective_rank": 11.632,
  "nonlinearity_score": 0.968016,
  "feature_target_alignment": 0.128655,
  "coef_l2_norm": 6.274934,
  "lasso_active_fraction": null,
  "circuit_depth": 1,
  "qubit_count": 10,
  "gate_count": 1,
  "model_name": "ridge",
  "chosen_alpha": 10.0,
  "seed": 42,
  "total_wall_clock": 0.0413
}