{
  "mse": 4.188361,
  "mae": 1.528116,
  "pearson_r": 0.939399,
  "mse_regime1": 2.598735,
  "mae_regime1": 1.275928,
  "pearson_r_regime1": 0.791613,
  "mse_regime2": 8.894282,
  "mae_regime2": 2.274694,
  "pearson_r_regime2": 0.926745,
  "mse_train": 4.116114,
  "mae_train": 1.519682,
  "pearson_r_train": 0.939968,
  "mse_train_regime1": 2.57248,
  "mse_train_regime2": 8.893666,
  "pearson_r_train_regime1": 0.791121,
  "pearson_r_train_regime2": 0.922885,
  "augmenter_name": "iqp_13q_r3",
  "n_features_total": 95,
  "n_features_augmented": 91,
  "augmenter_wall_clock": 73.7272,
  "n_trainable_params": 0,
  "n_random_params": 0,
  "effective_rank": 11.0026,
  "nonlinearity_score": 0.972258,
  "feature_target_alignment": 0.116522,
  "coef_l2_norm": 8.647379,
  "lasso_active_fraction": 0.715789,
  "circuit_depth": 1,
  "qubit_count": 13,
  "gate_count": 1,
  "model_name": "lasso",
  "chosen_alpha": 0.001,
  "seed": 42,
  "total_wall_clock": 0.0195
}