{
  "mse": 1.324524,
  "mae": 0.893215,
  "pearson_r": 0.981258,
  "mse_regime1": 1.157709,
  "mae_regime1": 0.851668,
  "pearson_r_regime1": 0.898522,
  "mse_regime2": 1.818361,
  "mae_regime2": 1.01621,
  "pearson_r_regime2": 0.974658,
  "mse_train": 1.252236,
  "mae_train": 0.877637,
  "pearson_r_train": 0.982127,
  "mse_train_regime1": 1.130646,
  "mse_train_regime2": 1.628557,
  "pearson_r_train_regime1": 0.89891,
  "pearson_r_train_regime2": 0.977431,
  "augmenter_name": "reservoir_24x3_X",
  "n_features_total": 100,
  "n_features_augmented": 96,
  "augmenter_wall_clock": 171.2549,
  "n_trainable_params": 0,
  "n_random_params": 864,
  "effective_rank": 24.8157,
  "nonlinearity_score": 0.662688,
  "feature_target_alignment": 0.284074,
  "coef_l2_norm": 14.096296,
  "lasso_active_fraction": 0.43,
  "circuit_depth": 11,
  "qubit_count": 4,
  "gate_count": 22,
  "model_name": "lasso",
  "chosen_alpha": 0.001,
  "seed": 42,
  "total_wall_clock": 0.1973
}