{
  "mse": 1.16318,
  "mae": 0.853125,
  "pearson_r": 0.983139,
  "mse_regime1": 1.099872,
  "mae_regime1": 0.837625,
  "pearson_r_regime1": 0.90287,
  "mse_regime2": 1.355454,
  "mae_regime2": 0.900202,
  "pearson_r_regime2": 0.980695,
  "mse_train": 1.060989,
  "mae_train": 0.820615,
  "pearson_r_train": 0.984808,
  "mse_train_regime1": 1.007242,
  "mse_train_regime2": 1.228515,
  "pearson_r_train_regime1": 0.910678,
  "pearson_r_train_regime2": 0.983057,
  "augmenter_name": "mlp_10",
  "n_features_total": 14,
  "n_features_augmented": 10,
  "augmenter_wall_clock": 0.0006,
  "circuit_depth": null,
  "qubit_count": null,
  "gate_count": null,
  "model_name": "ridge",
  "chosen_alpha": 10.0,
  "seed": 456,
  "total_wall_clock": 0.0189
}