{
  "mse": 2.722359,
  "mae": 1.263694,
  "pearson_r": 0.960247,
  "mse_regime1": 2.286619,
  "mae_regime1": 1.198908,
  "pearson_r_regime1": 0.786339,
  "mse_regime2": 4.016436,
  "mae_regime2": 1.456099,
  "pearson_r_regime2": 0.945274,
  "mse_train": 2.744251,
  "mae_train": 1.256746,
  "pearson_r_train": 0.958303,
  "mse_train_regime1": 2.284396,
  "mse_train_regime2": 4.227172,
  "pearson_r_train_regime1": 0.786883,
  "pearson_r_train_regime2": 0.943316,
  "augmenter_name": "unified_IQP_linear_noc_prob_2ens",
  "n_features_total": 36,
  "n_features_augmented": 32,
  "augmenter_wall_clock": 9.5453,
  "n_trainable_params": 0,
  "n_random_params": 0,
  "effective_rank": 6.1924,
  "nonlinearity_score": 0.874171,
  "feature_target_alignment": 0.293941,
  "coef_l2_norm": 25.395534,
  "lasso_active_fraction": null,
  "circuit_depth": 6,
  "qubit_count": 4,
  "gate_count": 15,
  "model_name": "ridge",
  "chosen_alpha": 0.1,
  "seed": 123,
  "total_wall_clock": 0.0302
}