{
  "mse": 1.341792,
  "mae": 0.902159,
  "pearson_r": 0.98061,
  "mse_regime1": 1.146906,
  "mae_regime1": 0.852811,
  "pearson_r_regime1": 0.896617,
  "mse_regime2": 1.920571,
  "mae_regime2": 1.048713,
  "pearson_r_regime2": 0.972163,
  "mse_train": 1.305978,
  "mae_train": 0.888881,
  "pearson_r_train": 0.980378,
  "mse_train_regime1": 1.155523,
  "mse_train_regime2": 1.791157,
  "pearson_r_train_regime1": 0.896782,
  "pearson_r_train_regime2": 0.974,
  "augmenter_name": "unified_angle_circular_noc_full_rot_2L_2ens",
  "n_features_total": 64,
  "n_features_augmented": 60,
  "augmenter_wall_clock": 28.3648,
  "n_trainable_params": 0,
  "n_random_params": 72,
  "effective_rank": 13.7291,
  "nonlinearity_score": 0.562935,
  "feature_target_alignment": 0.37732,
  "coef_l2_norm": 13.167244,
  "lasso_active_fraction": null,
  "circuit_depth": 4,
  "qubit_count": 4,
  "gate_count": 16,
  "model_name": "ridge",
  "chosen_alpha": 1.0,
  "seed": 123,
  "total_wall_clock": 0.0501
}