{
  "mse": 1.306189,
  "mae": 0.887911,
  "pearson_r": 0.98113,
  "mse_regime1": 1.125306,
  "mae_regime1": 0.842674,
  "pearson_r_regime1": 0.898719,
  "mse_regime2": 1.843378,
  "mae_regime2": 1.022259,
  "pearson_r_regime2": 0.973203,
  "mse_train": 1.254658,
  "mae_train": 0.875288,
  "pearson_r_train": 0.981156,
  "mse_train_regime1": 1.13509,
  "mse_train_regime2": 1.640238,
  "pearson_r_train_regime1": 0.898751,
  "pearson_r_train_regime2": 0.976222,
  "augmenter_name": "unified_angle_linear_cnot_full_rot_3L_2ens",
  "n_features_total": 64,
  "n_features_augmented": 60,
  "augmenter_wall_clock": 35.696,
  "n_trainable_params": 0,
  "n_random_params": 96,
  "effective_rank": 21.9708,
  "nonlinearity_score": 0.593963,
  "feature_target_alignment": 0.343851,
  "coef_l2_norm": 87.836897,
  "lasso_active_fraction": null,
  "circuit_depth": 12,
  "qubit_count": 4,
  "gate_count": 29,
  "model_name": "ridge",
  "chosen_alpha": 0.01,
  "seed": 123,
  "total_wall_clock": 0.0467
}