{
  "mse": 2.937675,
  "mae": 1.28082,
  "pearson_r": 0.957008,
  "mse_regime1": 2.218582,
  "mae_regime1": 1.162153,
  "pearson_r_regime1": 0.798373,
  "mse_regime2": 5.073258,
  "mae_regime2": 1.633241,
  "pearson_r_regime2": 0.926421,
  "mse_train": 2.864131,
  "mae_train": 1.264386,
  "pearson_r_train": 0.95644,
  "mse_train_regime1": 2.21084,
  "mse_train_regime2": 4.970837,
  "pearson_r_train_regime1": 0.800555,
  "pearson_r_train_regime2": 0.930209,
  "augmenter_name": "unified_IQP_all_cnot_Z+ZZ_rot_3L_3ens",
  "n_features_total": 34,
  "n_features_augmented": 30,
  "augmenter_wall_clock": 47.2693,
  "n_trainable_params": 0,
  "n_random_params": 144,
  "effective_rank": 20.4797,
  "nonlinearity_score": 0.790659,
  "feature_target_alignment": 0.190361,
  "coef_l2_norm": 10.379579,
  "lasso_active_fraction": null,
  "circuit_depth": 24,
  "qubit_count": 4,
  "gate_count": 52,
  "model_name": "ridge",
  "chosen_alpha": 1.0,
  "seed": 123,
  "total_wall_clock": 0.0283
}