{
  "mse": 2.359342,
  "mae": 1.169776,
  "pearson_r": 0.965628,
  "mse_regime1": 1.889889,
  "mae_regime1": 1.090793,
  "pearson_r_regime1": 0.823574,
  "mse_regime2": 3.753538,
  "mae_regime2": 1.404342,
  "pearson_r_regime2": 0.944306,
  "mse_train": 2.307161,
  "mae_train": 1.16134,
  "pearson_r_train": 0.965065,
  "mse_train_regime1": 1.879129,
  "mse_train_regime2": 3.68746,
  "pearson_r_train_regime1": 0.826042,
  "pearson_r_train_regime2": 0.945754,
  "augmenter_name": "unified_RZ_circular_cnot_prob_rot_2L",
  "n_features_total": 20,
  "n_features_augmented": 16,
  "augmenter_wall_clock": 8.7728,
  "n_trainable_params": 0,
  "n_random_params": 36,
  "effective_rank": 9.2574,
  "nonlinearity_score": 0.654682,
  "feature_target_alignment": 0.251084,
  "coef_l2_norm": 84.552316,
  "lasso_active_fraction": null,
  "circuit_depth": 14,
  "qubit_count": 4,
  "gate_count": 32,
  "model_name": "ridge",
  "chosen_alpha": 0.01,
  "seed": 123,
  "total_wall_clock": 0.0216
}