{
  "mse": 3.256925,
  "mae": 1.365801,
  "pearson_r": 0.952201,
  "mse_regime1": 2.530827,
  "mae_regime1": 1.252909,
  "pearson_r_regime1": 0.77712,
  "mse_regime2": 5.41331,
  "mae_regime2": 1.70107,
  "pearson_r_regime2": 0.927443,
  "mse_train": 3.280903,
  "mae_train": 1.357056,
  "pearson_r_train": 0.949934,
  "mse_train_regime1": 2.522776,
  "mse_train_regime2": 5.725677,
  "pearson_r_train_regime1": 0.779436,
  "pearson_r_train_regime2": 0.924852,
  "augmenter_name": "unified_IQP_all_cnot_XYZ_rot_3L",
  "n_features_total": 16,
  "n_features_augmented": 12,
  "augmenter_wall_clock": 13.4893,
  "n_trainable_params": 0,
  "n_random_params": 48,
  "effective_rank": 9.3169,
  "nonlinearity_score": 0.757108,
  "feature_target_alignment": 0.241609,
  "coef_l2_norm": 7.270232,
  "lasso_active_fraction": null,
  "circuit_depth": 24,
  "qubit_count": 4,
  "gate_count": 52,
  "model_name": "ridge",
  "chosen_alpha": 1.0,
  "seed": 123,
  "total_wall_clock": 0.0202
}