{
  "mse": 1.422603,
  "mae": 0.91997,
  "pearson_r": 0.979416,
  "mse_regime1": 1.200732,
  "mae_regime1": 0.869993,
  "pearson_r_regime1": 0.891512,
  "mse_regime2": 2.08152,
  "mae_regime2": 1.068393,
  "pearson_r_regime2": 0.969767,
  "mse_train": 1.389722,
  "mae_train": 0.911697,
  "pearson_r_train": 0.979106,
  "mse_train_regime1": 1.216974,
  "mse_train_regime2": 1.946794,
  "pearson_r_train_regime1": 0.89096,
  "pearson_r_train_regime2": 0.971717,
  "augmenter_name": "unified_angle_linear_noc_Z+ZZ_rot_2L_2ens",
  "n_features_total": 24,
  "n_features_augmented": 20,
  "augmenter_wall_clock": 16.7765,
  "n_trainable_params": 0,
  "n_random_params": 72,
  "effective_rank": 8.3595,
  "nonlinearity_score": 0.479465,
  "feature_target_alignment": 0.515152,
  "coef_l2_norm": 34.516493,
  "lasso_active_fraction": null,
  "circuit_depth": 4,
  "qubit_count": 4,
  "gate_count": 16,
  "model_name": "ridge",
  "chosen_alpha": 0.1,
  "seed": 123,
  "total_wall_clock": 0.0231
}