{
  "mse": 3.627125,
  "mae": 1.435531,
  "pearson_r": 0.946609,
  "mse_regime1": 2.415189,
  "mae_regime1": 1.2301,
  "pearson_r_regime1": 0.786256,
  "mse_regime2": 7.226366,
  "mae_regime2": 2.045624,
  "pearson_r_regime2": 0.925043,
  "mse_train": 3.636711,
  "mae_train": 1.422888,
  "pearson_r_train": 0.944346,
  "mse_train_regime1": 2.381243,
  "mse_train_regime2": 7.685292,
  "pearson_r_train_regime1": 0.789757,
  "pearson_r_train_regime2": 0.921166,
  "augmenter_name": "unified_IQP_all_noc_Z+ZZ_3ens",
  "n_features_total": 34,
  "n_features_augmented": 30,
  "augmenter_wall_clock": 23.2655,
  "n_trainable_params": 0,
  "n_random_params": 0,
  "effective_rank": 5.1487,
  "nonlinearity_score": 0.865018,
  "feature_target_alignment": 0.338785,
  "coef_l2_norm": 5.25665,
  "lasso_active_fraction": null,
  "circuit_depth": 8,
  "qubit_count": 4,
  "gate_count": 18,
  "model_name": "ridge",
  "chosen_alpha": 10.0,
  "seed": 123,
  "total_wall_clock": 0.0303
}