{
  "mse": 2.078161,
  "mae": 1.134385,
  "pearson_r": 0.969802,
  "mse_regime1": 2.159171,
  "mae_regime1": 1.164468,
  "pearson_r_regime1": 0.796582,
  "mse_regime2": 1.837575,
  "mae_regime2": 1.045043,
  "pearson_r_regime2": 0.973332,
  "mse_train": 2.128532,
  "mae_train": 1.137151,
  "pearson_r_train": 0.967815,
  "mse_train_regime1": 2.192863,
  "mse_train_regime2": 1.921079,
  "pearson_r_train_regime1": 0.794393,
  "pearson_r_train_regime2": 0.972695,
  "augmenter_name": "unified_RZ_linear_cnot_Z+ZZ_2L_2ens",
  "n_features_total": 24,
  "n_features_augmented": 20,
  "augmenter_wall_clock": 16.8626,
  "n_trainable_params": 0,
  "n_random_params": 0,
  "effective_rank": 5.0329,
  "nonlinearity_score": 0.837608,
  "feature_target_alignment": 0.369328,
  "coef_l2_norm": 5.677099,
  "lasso_active_fraction": null,
  "circuit_depth": 8,
  "qubit_count": 4,
  "gate_count": 18,
  "model_name": "ridge",
  "chosen_alpha": 10.0,
  "seed": 123,
  "total_wall_clock": 0.0297
}